<profile>

<ReportVersion>
<Version>2021.1</Version>
</ReportVersion>

<UserAssignments>
<unit>ns</unit>
<ProductFamily>zynq</ProductFamily>
<Part>xc7z020-clg400-1</Part>
<TopModelName>conv2d_stream_Pipeline_shift_up</TopModelName>
<TargetClockPeriod>10.00</TargetClockPeriod>
<ClockUncertainty>2.70</ClockUncertainty>
<FlowTarget>vivado</FlowTarget>
</UserAssignments>

<PerformanceEstimates>
<PipelineType>no</PipelineType>
<SummaryOfTimingAnalysis>
<unit>ns</unit>
<EstimatedClockPeriod>6.508</EstimatedClockPeriod>
</SummaryOfTimingAnalysis>
<SummaryOfOverallLatency>
<unit>clock cycles</unit>
<Best-caseLatency>70</Best-caseLatency>
<Average-caseLatency>70</Average-caseLatency>
<Worst-caseLatency>70</Worst-caseLatency>
<Best-caseRealTimeLatency>0.700 us</Best-caseRealTimeLatency>
<Average-caseRealTimeLatency>0.700 us</Average-caseRealTimeLatency>
<Worst-caseRealTimeLatency>0.700 us</Worst-caseRealTimeLatency>
<Interval-min>70</Interval-min>
<Interval-max>70</Interval-max>
</SummaryOfOverallLatency>
<SummaryOfLoopLatency>
<shift_up>
<TripCount>68</TripCount>
<Latency>68</Latency>
<AbsoluteTimeLatency>680</AbsoluteTimeLatency>
<PipelineII>1</PipelineII>
<PipelineDepth>2</PipelineDepth>
</shift_up>
</SummaryOfLoopLatency>
</PerformanceEstimates>

<AreaEstimates>
<Resources>
<FF>24</FF>
<LUT>62</LUT>
<BRAM_18K>0</BRAM_18K>
<DSP>0</DSP>
<URAM>0</URAM>
</Resources>
<AvailableResources>
<BRAM_18K>280</BRAM_18K>
<DSP>220</DSP>
<FF>106400</FF>
<LUT>53200</LUT>
<URAM>0</URAM>
</AvailableResources>
</AreaEstimates>

<InterfaceSummary>
<RtlPorts>
<name>ap_clk</name>
<Object>conv2d_stream_Pipeline_shift_up</Object>
<Type>return value</Type>
<Scope></Scope>
<IOProtocol>ap_ctrl_hs</IOProtocol>
<IOConfig></IOConfig>
<Dir>in</Dir>
<Bits>1</Bits>
<Attribute>control</Attribute>
</RtlPorts>
<RtlPorts>
<name>ap_rst</name>
<Object>conv2d_stream_Pipeline_shift_up</Object>
<Type>return value</Type>
<Scope></Scope>
<IOProtocol>ap_ctrl_hs</IOProtocol>
<IOConfig></IOConfig>
<Dir>in</Dir>
<Bits>1</Bits>
<Attribute>control</Attribute>
</RtlPorts>
<RtlPorts>
<name>ap_start</name>
<Object>conv2d_stream_Pipeline_shift_up</Object>
<Type>return value</Type>
<Scope></Scope>
<IOProtocol>ap_ctrl_hs</IOProtocol>
<IOConfig></IOConfig>
<Dir>in</Dir>
<Bits>1</Bits>
<Attribute>control</Attribute>
</RtlPorts>
<RtlPorts>
<name>ap_done</name>
<Object>conv2d_stream_Pipeline_shift_up</Object>
<Type>return value</Type>
<Scope></Scope>
<IOProtocol>ap_ctrl_hs</IOProtocol>
<IOConfig></IOConfig>
<Dir>out</Dir>
<Bits>1</Bits>
<Attribute>control</Attribute>
</RtlPorts>
<RtlPorts>
<name>ap_idle</name>
<Object>conv2d_stream_Pipeline_shift_up</Object>
<Type>return value</Type>
<Scope></Scope>
<IOProtocol>ap_ctrl_hs</IOProtocol>
<IOConfig></IOConfig>
<Dir>out</Dir>
<Bits>1</Bits>
<Attribute>control</Attribute>
</RtlPorts>
<RtlPorts>
<name>ap_ready</name>
<Object>conv2d_stream_Pipeline_shift_up</Object>
<Type>return value</Type>
<Scope></Scope>
<IOProtocol>ap_ctrl_hs</IOProtocol>
<IOConfig></IOConfig>
<Dir>out</Dir>
<Bits>1</Bits>
<Attribute>control</Attribute>
</RtlPorts>
<RtlPorts>
<name>linebuf_V_1_address0</name>
<Object>linebuf_V_1</Object>
<Type>array</Type>
<Scope></Scope>
<IOProtocol>ap_memory</IOProtocol>
<IOConfig></IOConfig>
<Dir>out</Dir>
<Bits>7</Bits>
<Attribute>address</Attribute>
</RtlPorts>
<RtlPorts>
<name>linebuf_V_1_ce0</name>
<Object>linebuf_V_1</Object>
<Type>array</Type>
<Scope></Scope>
<IOProtocol>ap_memory</IOProtocol>
<IOConfig></IOConfig>
<Dir>out</Dir>
<Bits>1</Bits>
<Attribute>control</Attribute>
</RtlPorts>
<RtlPorts>
<name>linebuf_V_1_we0</name>
<Object>linebuf_V_1</Object>
<Type>array</Type>
<Scope></Scope>
<IOProtocol>ap_memory</IOProtocol>
<IOConfig></IOConfig>
<Dir>out</Dir>
<Bits>1</Bits>
<Attribute>control</Attribute>
</RtlPorts>
<RtlPorts>
<name>linebuf_V_1_d0</name>
<Object>linebuf_V_1</Object>
<Type>array</Type>
<Scope></Scope>
<IOProtocol>ap_memory</IOProtocol>
<IOConfig></IOConfig>
<Dir>out</Dir>
<Bits>32</Bits>
<Attribute>data</Attribute>
</RtlPorts>
<RtlPorts>
<name>linebuf_V_1_address1</name>
<Object>linebuf_V_1</Object>
<Type>array</Type>
<Scope></Scope>
<IOProtocol>ap_memory</IOProtocol>
<IOConfig></IOConfig>
<Dir>out</Dir>
<Bits>7</Bits>
<Attribute>address</Attribute>
</RtlPorts>
<RtlPorts>
<name>linebuf_V_1_ce1</name>
<Object>linebuf_V_1</Object>
<Type>array</Type>
<Scope></Scope>
<IOProtocol>ap_memory</IOProtocol>
<IOConfig></IOConfig>
<Dir>out</Dir>
<Bits>1</Bits>
<Attribute>control</Attribute>
</RtlPorts>
<RtlPorts>
<name>linebuf_V_1_q1</name>
<Object>linebuf_V_1</Object>
<Type>array</Type>
<Scope></Scope>
<IOProtocol>ap_memory</IOProtocol>
<IOConfig></IOConfig>
<Dir>in</Dir>
<Bits>32</Bits>
<Attribute>data</Attribute>
</RtlPorts>
<RtlPorts>
<name>linebuf_V_0_address0</name>
<Object>linebuf_V_0</Object>
<Type>array</Type>
<Scope></Scope>
<IOProtocol>ap_memory</IOProtocol>
<IOConfig></IOConfig>
<Dir>out</Dir>
<Bits>7</Bits>
<Attribute>address</Attribute>
</RtlPorts>
<RtlPorts>
<name>linebuf_V_0_ce0</name>
<Object>linebuf_V_0</Object>
<Type>array</Type>
<Scope></Scope>
<IOProtocol>ap_memory</IOProtocol>
<IOConfig></IOConfig>
<Dir>out</Dir>
<Bits>1</Bits>
<Attribute>control</Attribute>
</RtlPorts>
<RtlPorts>
<name>linebuf_V_0_we0</name>
<Object>linebuf_V_0</Object>
<Type>array</Type>
<Scope></Scope>
<IOProtocol>ap_memory</IOProtocol>
<IOConfig></IOConfig>
<Dir>out</Dir>
<Bits>1</Bits>
<Attribute>control</Attribute>
</RtlPorts>
<RtlPorts>
<name>linebuf_V_0_d0</name>
<Object>linebuf_V_0</Object>
<Type>array</Type>
<Scope></Scope>
<IOProtocol>ap_memory</IOProtocol>
<IOConfig></IOConfig>
<Dir>out</Dir>
<Bits>32</Bits>
<Attribute>data</Attribute>
</RtlPorts>
<RtlPorts>
<name>linebuf_V_2_address0</name>
<Object>linebuf_V_2</Object>
<Type>array</Type>
<Scope></Scope>
<IOProtocol>ap_memory</IOProtocol>
<IOConfig></IOConfig>
<Dir>out</Dir>
<Bits>7</Bits>
<Attribute>address</Attribute>
</RtlPorts>
<RtlPorts>
<name>linebuf_V_2_ce0</name>
<Object>linebuf_V_2</Object>
<Type>array</Type>
<Scope></Scope>
<IOProtocol>ap_memory</IOProtocol>
<IOConfig></IOConfig>
<Dir>out</Dir>
<Bits>1</Bits>
<Attribute>control</Attribute>
</RtlPorts>
<RtlPorts>
<name>linebuf_V_2_we0</name>
<Object>linebuf_V_2</Object>
<Type>array</Type>
<Scope></Scope>
<IOProtocol>ap_memory</IOProtocol>
<IOConfig></IOConfig>
<Dir>out</Dir>
<Bits>1</Bits>
<Attribute>control</Attribute>
</RtlPorts>
<RtlPorts>
<name>linebuf_V_2_d0</name>
<Object>linebuf_V_2</Object>
<Type>array</Type>
<Scope></Scope>
<IOProtocol>ap_memory</IOProtocol>
<IOConfig></IOConfig>
<Dir>out</Dir>
<Bits>32</Bits>
<Attribute>data</Attribute>
</RtlPorts>
<RtlPorts>
<name>linebuf_V_2_q0</name>
<Object>linebuf_V_2</Object>
<Type>array</Type>
<Scope></Scope>
<IOProtocol>ap_memory</IOProtocol>
<IOConfig></IOConfig>
<Dir>in</Dir>
<Bits>32</Bits>
<Attribute>data</Attribute>
</RtlPorts>
</InterfaceSummary>

</profile>
